wagtailgatsby/__init__.py
wagtailgatsby/apps.py
wagtailgatsby/models.py
wagtailgatsby/wagtail_hooks.py
wagtailgatsby/migrations/0001_initial.py
wagtailgatsby/migrations/0002_gatsbyimage_gatsbyimagerendition.py
wagtailgatsby/migrations/0003_auto_20190807_1031.py
wagtailgatsby/migrations/__init__.py
wagtailgatsby-0.1.3.dist-info/METADATA
wagtailgatsby-0.1.3.dist-info/WHEEL
wagtailgatsby-0.1.3.dist-info/top_level.txt
wagtailgatsby-0.1.3.dist-info/RECORD
